bagmodels/__init__.py
bagmodels/models.py
bagmodels/tokenization.py
bagmodels-0.1.5.dist-info/LICENSE
bagmodels-0.1.5.dist-info/METADATA
bagmodels-0.1.5.dist-info/WHEEL
bagmodels-0.1.5.dist-info/top_level.txt
bagmodels-0.1.5.dist-info/RECORD
