Metadata-Version: 2.1
Name: bagmodels
Version: 0.1.5
Summary: BM25 NLP model
Home-page: https://github.com/HimanshuMittal01/bagmodels
Author: Himanshu Mittal
Author-email: himanshum1312@gmail.com
Project-URL: Bug Tracker, https://github.com/HimanshuMittal01/bagmodels/issues
Classifier: Programming Language :: Python :: 3
Classifier: License :: OSI Approved :: MIT License
Classifier: Operating System :: OS Independent
Requires-Python: >=3.6
License-File: LICENSE
Requires-Dist: joblib
